bilibili_data/__init__.py
bilibili_data/data_user.py
bilibili_data-0.0.6.dist-info/LICENSE
bilibili_data-0.0.6.dist-info/METADATA
bilibili_data-0.0.6.dist-info/WHEEL
bilibili_data-0.0.6.dist-info/top_level.txt
bilibili_data-0.0.6.dist-info/RECORD
